cryptosteganography/__init__.py
cryptosteganography/cli.py
cryptosteganography/utils.py
cryptosteganography-0.8.4.dist-info/LICENSE
cryptosteganography-0.8.4.dist-info/METADATA
cryptosteganography-0.8.4.dist-info/WHEEL
cryptosteganography-0.8.4.dist-info/entry_points.txt
cryptosteganography-0.8.4.dist-info/top_level.txt
cryptosteganography-0.8.4.dist-info/RECORD
