Metadata-Version: 2.1
Name: cryptosteganography
Version: 0.8.4
Summary: A python steganography module to store messages or files protected with AES-256 encryption inside an image.
Home-page: https://github.com/computationalcore/cryptosteganography
Author: Vin Busquet
Author-email: computationalcore@gmail.com
License: MIT
Classifier: Development Status :: 5 - Production/Stable
Classifier: Intended Audience :: Developers
Classifier: License :: OSI Approved :: MIT License
Classifier: Programming Language :: Python
Classifier: Programming Language :: Python :: 3
Classifier: Programming Language :: Python :: 3 :: Only
Classifier: Programming Language :: Python :: 3.9
Classifier: Programming Language :: Python :: 3.10
Classifier: Programming Language :: Python :: 3.11
Classifier: Programming Language :: Python :: 3.12
Requires-Python: >=3.9
License-File: LICENSE
Requires-Dist: colorama==0.4.6
Requires-Dist: crayons==0.4.0
Requires-Dist: exitstatus==2.5.0
Requires-Dist: numpy==2.0.0
Requires-Dist: opencv-python==4.10.0.84
Requires-Dist: piexif==1.1.3
Requires-Dist: pillow==10.3.0
Requires-Dist: pycryptodomex==3.20.0
Requires-Dist: stegano==0.11.3
Requires-Dist: setuptools==70.1.1
